{
  "hosting": {
    "amplifyhosting": {
      "service": "amplifyhosting",
      "type": "cicd",
      "lastPushTimeStamp": "2022-11-18T13:40:30.475Z"
    }
  },
  "api": {
    "landingpagetest": {
      "service": "AppSync",
      "providerPlugin": "awscloudformation",
      "dependsOn": [],
      "output": {
        "authConfig": {
          "defaultAuthentication": {
            "authenticationType": "API_KEY",
            "apiKeyConfig": {
              "apiKeyExpirationDays": 7
            }
          },
          "additionalAuthenticationProviders": []
        }
      }
    }
  }
}